{"nccFuncNode":{"funcNodeId":"27513246","serviceComp":"demoedittable2","codeStyle":"1","funcCode":"CH010105","funcName":"单表练习2","higerNodeCode":"CH0101","menuCode":"CH010105","menuName":"单表练习2","bmfFileName":"demoEtid2.bmf","entityCompName":"DemoEtid2","feat":"0","menuContentsName":"CH010105","menuResName":"单表练习2","menuResId":"APP_CH010105","dateField":"","moduleName":"asdf","aggClazz":"nc.vo.asdf.demoetid2.DemoEtid2","metaID":"9b8e1ce8-0c83-4613-94e9-d4b27d210b98","billType":"0000","metaName":"demoEtid2","parentBillType":"","databaseType":"ORACLE11G","appregisterCodes":[],"appmenuitemCodes":[],"groupList":[{"pk_group":"0001A210000000000EOV"}],"zipPaths":[]},"gen_model":[{"isMain":"true","swagger":"2.0","info":{"title":"commonTitle","x-pdmid":"commonPdmId"},"definitions":{"DemoEtid2":{"x-tableName":"asdf_DemoEtid2","description":"","title":"单表练习2","x-uititle":"单表练习2","x-namespace":"asdf","x-ownmodule":"asdf","name":"DemoEtid2","properties":{"pk_id":{"x-sortnumber":1,"x-isoperationinfo":"false","x-islist":"true","x-enums":[],"x-inputtype":"input","x-isreference":"false","ref-path":"","description":"","x-conlumname":"pk_id","type":"string","x-isqueryconfition":"true","default":"","x-ref-callback-des-properties":"","x-isUnique":"false","x-ref-path":"","x-conlumlength":"50","x-uitile":"主键","x-istransient":"false","x-ref-type":"","x-code-rule":"","proKey":"pk_id","x-ref-callback-src-properties":"","ref-type":"","ref-code":"","x-isdisplay":"true","x-iscode":"false","x-isrequired":"true","x-conlumtype":"char","x-queryconfition":"EQ","x-metaid":"","x-datatype":"1","x-refname":"","x-ref-meta":"","isKey":"true","x-isPk":"true","x-submodel":"","x-resId":"","x-maxvalue":"","x-minvalue":"","x-defaultvalue":"","isMainEntity":"false"},"pk_ass":{"x-sortnumber":2,"x-isoperationinfo":"false","x-islist":"true","x-enums":[],"x-inputtype":"refer","x-isreference":"true","ref-path":"","description":"","x-conlumname":"pk_ass","type":"string","x-isqueryconfition":"true","default":"","x-ref-callback-des-properties":"","x-isUnique":"false","x-ref-path":"fa/refer/newasset/facardTreeGridRef/index","x-conlumlength":"20","x-uitile":"资产类别","x-istransient":"false","x-ref-type":"","x-code-rule":"","proKey":"pk_ass","x-ref-callback-src-properties":"","ref-type":"","ref-code":"","x-isdisplay":"true","x-iscode":"false","x-isrequired":"false","x-conlumtype":"","x-queryconfition":"EQ","x-metaid":"8a1677c1-20f7-42ce-8798-24c74b7752de","x-datatype":"204","x-refname":"资产卡片","x-ref-meta":"fa.asset.asset_name","isKey":"false","x-isPk":"false","x-submodel":"","x-resId":"","x-maxvalue":"","x-minvalue":"","x-defaultvalue":"~","isMainEntity":"false"},"pk_group":{"x-sortnumber":3,"x-isoperationinfo":"false","x-islist":"true","x-enums":[],"x-inputtype":"refer","x-isreference":"true","ref-path":"","description":"","x-conlumname":"pk_group","type":"string","x-isqueryconfition":"true","default":"","x-ref-callback-des-properties":"","x-isUnique":"false","x-ref-path":"uapbd/refer/org/GroupDefaultTreeRef/index","x-conlumlength":"20","x-uitile":"集团","x-istransient":"false","x-ref-type":"","x-code-rule":"","proKey":"pk_group","x-ref-callback-src-properties":"","ref-type":"","ref-code":"","x-isdisplay":"true","x-iscode":"false","x-isrequired":"false","x-conlumtype":"","x-queryconfition":"EQ","x-metaid":"3b6dd171-2900-47f3-bfbe-41e4483a2a65","x-datatype":"204","x-refname":"集团(所有)","x-ref-meta":"uap.group.name","isKey":"false","x-isPk":"false","x-submodel":"","x-resId":"","x-maxvalue":"","x-minvalue":"","x-defaultvalue":"~","isMainEntity":"false"},"pk_depa":{"x-sortnumber":4,"x-isoperationinfo":"false","x-islist":"true","x-enums":[],"x-inputtype":"input","x-isreference":"false","ref-path":"","description":"","x-conlumname":"pk_depa","type":"string","x-isqueryconfition":"true","default":"","x-ref-callback-des-properties":"","x-isUnique":"false","x-ref-path":"asdf/refer/refer/DemotreeVOTreeRef/index","x-conlumlength":"50","x-uitile":"部门分类","x-istransient":"false","x-ref-type":"","x-code-rule":"","proKey":"pk_depa","x-ref-callback-src-properties":"","ref-type":"","ref-code":"","x-isdisplay":"true","x-iscode":"false","x-isrequired":"false","x-conlumtype":"varchar","x-queryconfition":"EQ","x-metaid":"","x-datatype":"1","x-refname":"部门分类","x-ref-meta":"","isKey":"false","x-isPk":"false","x-submodel":"","x-resId":"","x-maxvalue":"","x-minvalue":"","x-defaultvalue":"","isMainEntity":"false"},"demo2_name_":{"x-sortnumber":5,"x-isoperationinfo":"false","x-islist":"true","x-enums":[],"x-inputtype":"input","x-isreference":"false","ref-path":"","description":"","x-conlumname":"demo2_name_","type":"string","x-isqueryconfition":"true","default":"","x-ref-callback-des-properties":"","x-isUnique":"false","x-ref-path":"","x-conlumlength":"50","x-uitile":"名称","x-istransient":"false","x-ref-type":"","x-code-rule":"","proKey":"demo2_name_","x-ref-callback-src-properties":"","ref-type":"","ref-code":"","x-isdisplay":"true","x-iscode":"false","x-isrequired":"false","x-conlumtype":"varchar","x-queryconfition":"EQ","x-metaid":"","x-datatype":"1","x-refname":"","x-ref-meta":"","isKey":"false","x-isPk":"false","x-submodel":"","x-resId":"","x-maxvalue":"","x-minvalue":"","x-defaultvalue":"","isMainEntity":"false"},"demo_enum":{"x-sortnumber":6,"x-isoperationinfo":"false","x-islist":"true","x-enums":[{"key":"1","value":"枚举选项1"},{"key":"2","value":"枚举选项2"},{"key":"3","value":"枚举选项3"}],"x-inputtype":"select","x-isreference":"false","ref-path":"","description":"","x-conlumname":"demo_enum","type":"string","x-isqueryconfition":"true","default":"","x-ref-callback-des-properties":"","x-isUnique":"false","x-ref-path":"","x-conlumlength":"50","x-uitile":"枚举","x-istransient":"false","x-ref-type":"","x-code-rule":"","proKey":"demo_enum","x-ref-callback-src-properties":"","ref-type":"","ref-code":"","x-isdisplay":"true","x-iscode":"false","x-isrequired":"false","x-conlumtype":"","x-queryconfition":"EQ","x-metaid":"","x-datatype":"203","x-refname":"","x-ref-meta":"","isKey":"false","x-isPk":"false","x-submodel":"","x-resId":"","x-maxvalue":"","x-minvalue":"","x-defaultvalue":"","isMainEntity":"false"},"def2":{"x-sortnumber":7,"x-isoperationinfo":"false","x-islist":"false","x-enums":[],"x-inputtype":"input","x-isreference":"false","ref-path":"","description":"","x-conlumname":"def2","type":"string","x-isqueryconfition":"false","default":"","x-ref-callback-des-properties":"","x-isUnique":"false","x-ref-path":"","x-conlumlength":"101","x-uitile":"自定义项2","x-istransient":"false","x-ref-type":"","x-code-rule":"","proKey":"def2","x-ref-callback-src-properties":"","ref-type":"","ref-code":"","x-isdisplay":"false","x-iscode":"false","x-isrequired":"false","x-conlumtype":"varchar","x-queryconfition":"EQ","x-metaid":"","x-datatype":"1","x-refname":"","x-ref-meta":"","isKey":"false","x-isPk":"false","x-submodel":"","x-resId":"","x-maxvalue":"","x-minvalue":"","x-defaultvalue":"","isMainEntity":"false"},"def3":{"x-sortnumber":8,"x-isoperationinfo":"false","x-islist":"false","x-enums":[],"x-inputtype":"input","x-isreference":"false","ref-path":"","description":"","x-conlumname":"def3","type":"string","x-isqueryconfition":"false","default":"","x-ref-callback-des-properties":"","x-isUnique":"false","x-ref-path":"","x-conlumlength":"101","x-uitile":"自定义项3","x-istransient":"false","x-ref-type":"","x-code-rule":"","proKey":"def3","x-ref-callback-src-properties":"","ref-type":"","ref-code":"","x-isdisplay":"false","x-iscode":"false","x-isrequired":"false","x-conlumtype":"varchar","x-queryconfition":"EQ","x-metaid":"","x-datatype":"1","x-refname":"","x-ref-meta":"","isKey":"false","x-isPk":"false","x-submodel":"","x-resId":"","x-maxvalue":"","x-minvalue":"","x-defaultvalue":"","isMainEntity":"false"},"def4":{"x-sortnumber":9,"x-isoperationinfo":"false","x-islist":"false","x-enums":[],"x-inputtype":"input","x-isreference":"false","ref-path":"","description":"","x-conlumname":"def4","type":"string","x-isqueryconfition":"false","default":"","x-ref-callback-des-properties":"","x-isUnique":"false","x-ref-path":"","x-conlumlength":"101","x-uitile":"自定义项4","x-istransient":"false","x-ref-type":"","x-code-rule":"","proKey":"def4","x-ref-callback-src-properties":"","ref-type":"","ref-code":"","x-isdisplay":"false","x-iscode":"false","x-isrequired":"false","x-conlumtype":"varchar","x-queryconfition":"EQ","x-metaid":"","x-datatype":"1","x-refname":"","x-ref-meta":"","isKey":"false","x-isPk":"false","x-submodel":"","x-resId":"","x-maxvalue":"","x-minvalue":"","x-defaultvalue":"","isMainEntity":"false"},"def5":{"x-sortnumber":10,"x-isoperationinfo":"false","x-islist":"false","x-enums":[],"x-inputtype":"input","x-isreference":"false","ref-path":"","description":"","x-conlumname":"def5","type":"string","x-isqueryconfition":"false","default":"","x-ref-callback-des-properties":"","x-isUnique":"false","x-ref-path":"","x-conlumlength":"101","x-uitile":"自定义项5","x-istransient":"false","x-ref-type":"","x-code-rule":"","proKey":"def5","x-ref-callback-src-properties":"","ref-type":"","ref-code":"","x-isdisplay":"false","x-iscode":"false","x-isrequired":"false","x-conlumtype":"varchar","x-queryconfition":"EQ","x-metaid":"","x-datatype":"1","x-refname":"","x-ref-meta":"","isKey":"false","x-isPk":"false","x-submodel":"","x-resId":"","x-maxvalue":"","x-minvalue":"","x-defaultvalue":"","isMainEntity":"false"}},"isMain":"true","x-entityId":"9b8e1ce8-0c83-4613-94e9-d4b27d210b98","x-clazz":"nc.vo.asdf.demoetid2.DemoEtid2","x-pkName":"pk_id","x-isTreeEntity":"false","x-sonattrname":""}}}],"pkGenModel":"366edfd4-192a-4501-a0df-bdf23b5bb070","modelName":"demoEtid2","lastModified":"May 6, 2020 6:48:21 PM","createUser":"yonyouBQ"}